gapps/__init__.py
gapps/_version.py
gapps/cardservice/__init__.py
gapps/cardservice/api.py
gapps/cardservice/constants.py
gapps/cardservice/decorators.py
gapps/cardservice/models.py
gapps/cardservice/utilities.py
gapps/cardservice/tests/__init__.py
gapps/cardservice/tests/test_cards.py
gapps/cardservice/tests/test_decorators.py
gapps/cardservice/tests/test_utilities.py
gapps-0.1.1.dist-info/AUTHORS.rst
gapps-0.1.1.dist-info/LICENSE
gapps-0.1.1.dist-info/METADATA
gapps-0.1.1.dist-info/WHEEL
gapps-0.1.1.dist-info/top_level.txt
gapps-0.1.1.dist-info/RECORD
