Metadata-Version: 2.1
Name: gapps
Version: 0.1.1
Summary: python interface of the google apps service
Author-email: Serge Koudoro <skab12@gmail.com>
License: MIT License
Project-URL: Documentation, https://github.com/skoudoro/gapps/tree/main#readme
Project-URL: Source, https://github.com/skoudoro/gapps
Project-URL: Tracker, https://github.com/skoudoro/gapps/issues
Keywords: appscript,cardservice,google workspace add-ons,docs,sheet,calendar,gmail,forms,slide,drive
Classifier: Development Status :: 3 - Alpha
Classifier: Intended Audience :: Developers
Classifier: License :: OSI Approved :: MIT License
Classifier: Programming Language :: Python :: 3 :: Only
Classifier: Programming Language :: Python :: 3.8
Classifier: Programming Language :: Python :: 3.9
Classifier: Programming Language :: Python :: 3.10
Classifier: Programming Language :: Python :: 3.11
Requires-Python: >=3.9
License-File: LICENSE
License-File: AUTHORS.rst
Requires-Dist: pep517 >=0.9.1
Requires-Dist: dataclasses-json >=0.5.7
Requires-Dist: pydantic >=1.9.0
Requires-Dist: google-auth >=2.12.0
Requires-Dist: requests
Provides-Extra: demo
Requires-Dist: fastapi ; extra == 'demo'
Requires-Dist: uvicorn ; extra == 'demo'
Requires-Dist: google-api-python-client >=2.68.0 ; extra == 'demo'
Provides-Extra: docs
Requires-Dist: codecov ; extra == 'docs'
Requires-Dist: coverage ; extra == 'docs'
Requires-Dist: flake8 ; extra == 'docs'
Requires-Dist: pytest ; extra == 'docs'
Requires-Dist: sphinx ; extra == 'docs'
Requires-Dist: ipython ; extra == 'docs'
Requires-Dist: ipdb ; extra == 'docs'
Requires-Dist: matplotlib ; extra == 'docs'
Requires-Dist: numpydoc ; extra == 'docs'
Requires-Dist: sphinx-copybutton ; extra == 'docs'
Requires-Dist: sphinx-rtd-theme ; extra == 'docs'
Requires-Dist: responses ; extra == 'docs'
Provides-Extra: test
Requires-Dist: black ==22.1.0 ; extra == 'test'
Requires-Dist: flake8 ==4.0.1 ; extra == 'test'
Requires-Dist: pre-commit ==2.17.0 ; extra == 'test'
Requires-Dist: pylint ==2.12.2 ; extra == 'test'
Requires-Dist: pytest ==7.1.0 ; extra == 'test'
Requires-Dist: pip-conflict-checker >=0.6.0 ; extra == 'test'
Provides-Extra: typing
Requires-Dist: importlib-metadata >=5.1 ; extra == 'typing'
Requires-Dist: mypy ==0.991 ; extra == 'typing'
Requires-Dist: tomli ; extra == 'typing'
Requires-Dist: typing-extensions >=3.7.4.3 ; extra == 'typing'
